stuart/__init__.py
stuart/app.py
stuart/main.py
stuart/systems.py
stuart/wsgi.py
stuart-0.2.0.dist-info/LICENSE
stuart-0.2.0.dist-info/METADATA
stuart-0.2.0.dist-info/WHEEL
stuart-0.2.0.dist-info/top_level.txt
stuart-0.2.0.dist-info/RECORD
