Metadata-Version: 2.1
Name: stuart
Version: 0.2.0
Summary: A self-hostable game data aggregator for Elite: Dangerous
License: GNU AFFERO GENERAL PUBLIC LICENSE
Classifier: Development Status :: 1 - Planning
Classifier: Environment :: No Input/Output (Daemon)
Classifier: Framework :: Flask
Classifier: Intended Audience :: System Administrators
Classifier: License :: OSI Approved :: GNU Affero General Public License v3 or later (AGPLv3+)
Classifier: Operating System :: OS Independent
Classifier: Programming Language :: Python
Classifier: Topic :: Database :: Front-Ends
Classifier: Topic :: Internet :: WWW/HTTP :: WSGI :: Application
Classifier: Topic :: Games/Entertainment :: Simulation
Classifier: Topic :: Utilities
Requires-Python: >=3.10
License-File: LICENSE
Requires-Dist: bootstrap-flask
Requires-Dist: flask
Requires-Dist: flask-sqlalchemy
Requires-Dist: flask-talisman
Requires-Dist: flask-wtf
Requires-Dist: gunicorn
Requires-Dist: lethbridge
Provides-Extra: dev
Requires-Dist: autopep8 ; extra == 'dev'
Requires-Dist: black ; extra == 'dev'
Requires-Dist: build ; extra == 'dev'
Requires-Dist: flake8 ; extra == 'dev'
Requires-Dist: isort ; extra == 'dev'
Requires-Dist: id ; extra == 'dev'
Requires-Dist: jedi ; extra == 'dev'
Requires-Dist: pip-tools ; extra == 'dev'
Requires-Dist: pre-commit ; extra == 'dev'
Requires-Dist: python-semantic-release ; extra == 'dev'
Requires-Dist: twine ; extra == 'dev'
Requires-Dist: yapf ; extra == 'dev'
Requires-Dist: yq ; extra == 'dev'
Provides-Extra: psycopg2
Requires-Dist: psycopg2 ; extra == 'psycopg2'
Provides-Extra: psycopg2cffi
Requires-Dist: psycopg2cffi ; extra == 'psycopg2cffi'
Provides-Extra: test
Requires-Dist: psycopg2 ; extra == 'test'
Requires-Dist: pytest ; extra == 'test'
Requires-Dist: pytest-cov ; extra == 'test'
Requires-Dist: pytest-emoji ; extra == 'test'
Requires-Dist: pytest-flask ; extra == 'test'
Requires-Dist: pytest-md ; extra == 'test'
Requires-Dist: pytest-order ; extra == 'test'
Requires-Dist: pytest-postgresql ; extra == 'test'
Requires-Dist: pytest-reportlog ; extra == 'test'
Requires-Dist: simplejson ; extra == 'test'
